{"matches":[{"id":"fs_M5yj09Dr","source":"flashscore","league":"Football","league_url":null,"home_team":"Gimnasia Jujuy","away_team":"Chacarita Juniors","kickoff":null,"status":"live","minute":60,"score":{"home":0,"away":1},"match_url":"https://www.flashscore.com/match/M5yj09Dr/","tip":{"market":"Over 1.5 golova","confidence":57,"stars":3,"explanation":"Rezultat 0-1 u 60'. min, ostalo 30 min. Chacarita Juniors dominira — posedovanje 50%, šutevi na gol 0. xG: 0.00-0.00. Momentum: Gimnasia Jujuy 50% / Chacarita Juniors 50%.","key_factors":["xG: Gimnasia Jujuy 0.00 — Chacarita Juniors 0.00","Posedovanje: 50% — 50%","Šutevi na gol: 0 — 0","Momentum: Gimnasia Jujuy 50% / Chacarita Juniors 50%","Preostalo: 30 min"],"stats_breakdown":{"momentum_home":0.5,"momentum_away":0.5,"xg_home":0.0,"xg_away":0.0,"all_markets":{"Domaćin pobeđuje [0-1]":23,"Remi [0-1]":47,"Gost pobeđuje [0-1]":30,"Over 1.5 golova":57}}}},{"id":"fs_QgGOHYTb","source":"flashscore","league":"Football","league_url":null,"home_team":"Colon Santa Fe","away_team":"Central Norte","kickoff":null,"status":"live","minute":null,"score":{"home":2,"away":0},"match_url":"https://www.flashscore.com/match/QgGOHYTb/","tip":{"market":"Over 2.5 golova","confidence":71,"stars":4,"explanation":"Rezultat 2-0 u 45'. min, ostalo 45 min. Central Norte dominira — posedovanje 50%, šutevi na gol 0. xG: 0.00-0.00. Momentum: Colon Santa Fe 50% / Central Norte 50%.","key_factors":["xG: Colon Santa Fe 0.00 — Central Norte 0.00","Posedovanje: 50% — 50%","Šutevi na gol: 0 — 0","Momentum: Colon Santa Fe 50% / Central Norte 50%","Preostalo: 45 min"],"stats_breakdown":{"momentum_home":0.5,"momentum_away":0.5,"xg_home":0.0,"xg_away":0.0,"all_markets":{"Domaćin pobeđuje [2-0]":35,"Remi [2-0]":37,"Gost pobeđuje [2-0]":27,"Over 2.5 golova":71}}}},{"id":"fs_IiLhKU4E","source":"flashscore","league":"Football","league_url":null,"home_team":"Agropecuario","away_team":"Temperley","kickoff":null,"status":"live","minute":26,"score":{"home":0,"away":0},"match_url":"https://www.flashscore.com/match/IiLhKU4E/","tip":{"market":"Over 0.5 golova","confidence":83,"stars":4,"explanation":"Rezultat 0-0 u 26'. min, ostalo 64 min. Temperley dominira — posedovanje 50%, šutevi na gol 0. xG: 0.00-0.00. Momentum: Agropecuario 50% / Temperley 50%.","key_factors":["xG: Agropecuario 0.00 — Temperley 0.00","Posedovanje: 50% — 50%","Šutevi na gol: 0 — 0","Momentum: Agropecuario 50% / Temperley 50%","Preostalo: 64 min"],"stats_breakdown":{"momentum_home":0.5,"momentum_away":0.5,"xg_home":0.0,"xg_away":0.0,"all_markets":{"Domaćin pobeđuje [0-0]":34,"Remi [0-0]":33,"Gost pobeđuje [0-0]":34,"Over 0.5 golova":83}}}},{"id":"fs_fJZcbmre","source":"flashscore","league":"Football","league_url":null,"home_team":"Club A. Guemes","away_team":"San Martin S.J.","kickoff":null,"status":"live","minute":20,"score":{"home":0,"away":1},"match_url":"https://www.flashscore.com/match/fJZcbmre/","tip":{"market":"Over 1.5 golova","confidence":86,"stars":4,"explanation":"Rezultat 0-1 u 20'. min, ostalo 70 min. San Martin S.J. dominira — posedovanje 50%, šutevi na gol 0. xG: 0.00-0.00. Momentum: Club A. Guemes 50% / San Martin S.J. 50%.","key_factors":["xG: Club A. Guemes 0.00 — San Martin S.J. 0.00","Posedovanje: 50% — 50%","Šutevi na gol: 0 — 0","Momentum: Club A. Guemes 50% / San Martin S.J. 50%","Preostalo: 70 min"],"stats_breakdown":{"momentum_home":0.5,"momentum_away":0.5,"xg_home":0.0,"xg_away":0.0,"all_markets":{"Domaćin pobeđuje [0-1]":31,"Remi [0-1]":28,"Gost pobeđuje [0-1]":41,"Over 1.5 golova":86}}}},{"id":"fs_YTUzX7lK","source":"flashscore","league":"Football","league_url":null,"home_team":"Midland","away_team":"Quilmes","kickoff":null,"status":"live","minute":24,"score":{"home":0,"away":0},"match_url":"https://www.flashscore.com/match/YTUzX7lK/","tip":{"market":"Over 0.5 golova","confidence":84,"stars":4,"explanation":"Rezultat 0-0 u 24'. min, ostalo 66 min. Quilmes dominira — posedovanje 50%, šutevi na gol 0. xG: 0.00-0.00. Momentum: Midland 50% / Quilmes 50%.","key_factors":["xG: Midland 0.00 — Quilmes 0.00","Posedovanje: 50% — 50%","Šutevi na gol: 0 — 0","Momentum: Midland 50% / Quilmes 50%","Preostalo: 66 min"],"stats_breakdown":{"momentum_home":0.5,"momentum_away":0.5,"xg_home":0.0,"xg_away":0.0,"all_markets":{"Domaćin pobeđuje [0-0]":34,"Remi [0-0]":32,"Gost pobeđuje [0-0]":34,"Over 0.5 golova":84}}}},{"id":"fs_WY7dEaN6","source":"flashscore","league":"Football","league_url":null,"home_team":"Racing Cordoba","away_team":"Acassuso","kickoff":null,"status":"live","minute":27,"score":{"home":0,"away":0},"match_url":"https://www.flashscore.com/match/WY7dEaN6/","tip":{"market":"Over 0.5 golova","confidence":83,"stars":4,"explanation":"Rezultat 0-0 u 27'. min, ostalo 63 min. Acassuso dominira — posedovanje 50%, šutevi na gol 0. xG: 0.00-0.00. Momentum: Racing Cordoba 50% / Acassuso 50%.","key_factors":["xG: Racing Cordoba 0.00 — Acassuso 0.00","Posedovanje: 50% — 50%","Šutevi na gol: 0 — 0","Momentum: Racing Cordoba 50% / Acassuso 50%","Preostalo: 63 min"],"stats_breakdown":{"momentum_home":0.5,"momentum_away":0.5,"xg_home":0.0,"xg_away":0.0,"all_markets":{"Domaćin pobeđuje [0-0]":33,"Remi [0-0]":33,"Gost pobeđuje [0-0]":33,"Over 0.5 golova":83}}}},{"id":"fs_jDWsObft","source":"flashscore","league":"Football","league_url":null,"home_team":"Circulo Deportivo","away_team":"Sol de Mayo","kickoff":null,"status":"live","minute":64,"score":{"home":3,"away":0},"match_url":"https://www.flashscore.com/match/jDWsObft/","tip":{"market":"Remi [3-0]","confidence":51,"stars":3,"explanation":"Rezultat 3-0 u 64'. min, ostalo 26 min. Sol de Mayo dominira — posedovanje 50%, šutevi na gol 0. xG: 0.00-0.00. Momentum: Circulo Deportivo 50% / Sol de Mayo 50%.","key_factors":["xG: Circulo Deportivo 0.00 — Sol de Mayo 0.00","Posedovanje: 50% — 50%","Šutevi na gol: 0 — 0","Momentum: Circulo Deportivo 50% / Sol de Mayo 50%","Preostalo: 26 min"],"stats_breakdown":{"momentum_home":0.5,"momentum_away":0.5,"xg_home":0.0,"xg_away":0.0,"all_markets":{"Domaćin pobeđuje [3-0]":28,"Remi [3-0]":51,"Gost pobeđuje [3-0]":21,"Over 3.5 golova":51}}}},{"id":"fs_YHRZbgsI","source":"flashscore","league":"Football","league_url":null,"home_team":"El Linqueno","away_team":"Independiente Chivilcoy","kickoff":null,"status":"live","minute":66,"score":{"home":2,"away":0},"match_url":"https://www.flashscore.com/match/YHRZbgsI/","tip":{"market":"Remi [2-0]","confidence":53,"stars":3,"explanation":"Rezultat 2-0 u 66'. min, ostalo 24 min. Independiente Chivilcoy dominira — posedovanje 50%, šutevi na gol 0. xG: 0.00-0.00. Momentum: El Linqueno 50% / Independiente Chivilcoy 50%.","key_factors":["xG: El Linqueno 0.00 — Independiente Chivilcoy 0.00","Posedovanje: 50% — 50%","Šutevi na gol: 0 — 0","Momentum: El Linqueno 50% / Independiente Chivilcoy 50%","Preostalo: 24 min"],"stats_breakdown":{"momentum_home":0.5,"momentum_away":0.5,"xg_home":0.0,"xg_away":0.0,"all_markets":{"Domaćin pobeđuje [2-0]":27,"Remi [2-0]":53,"Gost pobeđuje [2-0]":20,"Over 2.5 golova":49}}}},{"id":"fs_4zwbKGg5","source":"flashscore","league":"Football","league_url":null,"home_team":"Germinal","away_team":"Olimpo Bahia Blanca","kickoff":null,"status":"live","minute":64,"score":{"home":0,"away":1},"match_url":"https://www.flashscore.com/match/4zwbKGg5/","tip":{"market":"Remi [0-1]","confidence":51,"stars":3,"explanation":"Rezultat 0-1 u 64'. min, ostalo 26 min. Olimpo Bahia Blanca dominira — posedovanje 50%, šutevi na gol 0. xG: 0.00-0.00. Momentum: Germinal 50% / Olimpo Bahia Blanca 50%.","key_factors":["xG: Germinal 0.00 — Olimpo Bahia Blanca 0.00","Posedovanje: 50% — 50%","Šutevi na gol: 0 — 0","Momentum: Germinal 50% / Olimpo Bahia Blanca 50%","Preostalo: 26 min"],"stats_breakdown":{"momentum_home":0.5,"momentum_away":0.5,"xg_home":0.0,"xg_away":0.0,"all_markets":{"Domaćin pobeđuje [0-1]":21,"Remi [0-1]":51,"Gost pobeđuje [0-1]":28,"Over 1.5 golova":51}}}},{"id":"fs_tKp7Ms97","source":"flashscore","league":"Football","league_url":null,"home_team":"Sol de America","away_team":"Boca Unidos","kickoff":null,"status":"live","minute":69,"score":{"home":1,"away":2},"match_url":"https://www.flashscore.com/match/tKp7Ms97/","tip":{"market":"Remi [1-2]","confidence":56,"stars":3,"explanation":"Rezultat 1-2 u 69'. min, ostalo 21 min. Boca Unidos dominira — posedovanje 50%, šutevi na gol 0. xG: 0.00-0.00. Momentum: Sol de America 50% / Boca Unidos 50%.","key_factors":["xG: Sol de America 0.00 — Boca Unidos 0.00","Posedovanje: 50% — 50%","Šutevi na gol: 0 — 0","Momentum: Sol de America 50% / Boca Unidos 50%","Preostalo: 21 min"],"stats_breakdown":{"momentum_home":0.5,"momentum_away":0.5,"xg_home":0.0,"xg_away":0.0,"all_markets":{"Domaćin pobeđuje [1-2]":19,"Remi [1-2]":56,"Gost pobeđuje [1-2]":25,"Over 3.5 golova":44}}}},{"id":"fs_bwzjMxPh","source":"flashscore","league":"Football","league_url":null,"home_team":"Villa Mitre","away_team":"Guillermo Brown","kickoff":null,"status":"live","minute":69,"score":{"home":3,"away":0},"match_url":"https://www.flashscore.com/match/bwzjMxPh/","tip":{"market":"Remi [3-0]","confidence":56,"stars":3,"explanation":"Rezultat 3-0 u 69'. min, ostalo 21 min. Guillermo Brown dominira — posedovanje 50%, šutevi na gol 0. xG: 0.00-0.00. Momentum: Villa Mitre 50% / Guillermo Brown 50%.","key_factors":["xG: Villa Mitre 0.00 — Guillermo Brown 0.00","Posedovanje: 50% — 50%","Šutevi na gol: 0 — 0","Momentum: Villa Mitre 50% / Guillermo Brown 50%","Preostalo: 21 min"],"stats_breakdown":{"momentum_home":0.5,"momentum_away":0.5,"xg_home":0.0,"xg_away":0.0,"all_markets":{"Domaćin pobeđuje [3-0]":25,"Remi [3-0]":56,"Gost pobeđuje [3-0]":19,"Over 3.5 golova":44}}}},{"id":"fs_CMRWx3gl","source":"flashscore","league":"Football","league_url":null,"home_team":"Bartolome Mitre","away_team":"Defensores de Vilelas","kickoff":null,"status":"live","minute":null,"score":{"home":0,"away":0},"match_url":"https://www.flashscore.com/match/CMRWx3gl/","tip":{"market":"Over 0.5 golova","confidence":71,"stars":4,"explanation":"Rezultat 0-0 u 45'. min, ostalo 45 min. Defensores de Vilelas dominira — posedovanje 50%, šutevi na gol 0. xG: 0.00-0.00. Momentum: Bartolome Mitre 50% / Defensores de Vilelas 50%.","key_factors":["xG: Bartolome Mitre 0.00 — Defensores de Vilelas 0.00","Posedovanje: 50% — 50%","Šutevi na gol: 0 — 0","Momentum: Bartolome Mitre 50% / Defensores de Vilelas 50%","Preostalo: 45 min"],"stats_breakdown":{"momentum_home":0.5,"momentum_away":0.5,"xg_home":0.0,"xg_away":0.0,"all_markets":{"Domaćin pobeđuje [0-0]":30,"Remi [0-0]":41,"Gost pobeđuje [0-0]":30,"Over 0.5 golova":71}}}},{"id":"fs_APsBWk8l","source":"flashscore","league":"Football","league_url":null,"home_team":"Deportivo Rincon","away_team":"Huracan Las Heras","kickoff":null,"status":"live","minute":45,"score":{"home":0,"away":0},"match_url":"https://www.flashscore.com/match/APsBWk8l/","tip":{"market":"Over 0.5 golova","confidence":71,"stars":4,"explanation":"Rezultat 0-0 u 45'. min, ostalo 45 min. Huracan Las Heras dominira — posedovanje 50%, šutevi na gol 0. xG: 0.00-0.00. Momentum: Deportivo Rincon 50% / Huracan Las Heras 50%.","key_factors":["xG: Deportivo Rincon 0.00 — Huracan Las Heras 0.00","Posedovanje: 50% — 50%","Šutevi na gol: 0 — 0","Momentum: Deportivo Rincon 50% / Huracan Las Heras 50%","Preostalo: 45 min"],"stats_breakdown":{"momentum_home":0.5,"momentum_away":0.5,"xg_home":0.0,"xg_away":0.0,"all_markets":{"Domaćin pobeđuje [0-0]":30,"Remi [0-0]":41,"Gost pobeđuje [0-0]":30,"Over 0.5 golova":71}}}},{"id":"fs_YDXhpo1E","source":"flashscore","league":"Football","league_url":null,"home_team":"Juventud Antoniana","away_team":"Tucuman Central","kickoff":null,"status":"live","minute":null,"score":{"home":1,"away":0},"match_url":"https://www.flashscore.com/match/YDXhpo1E/","tip":{"market":"Over 1.5 golova","confidence":71,"stars":4,"explanation":"Rezultat 1-0 u 45'. min, ostalo 45 min. Tucuman Central dominira — posedovanje 50%, šutevi na gol 0. xG: 0.00-0.00. Momentum: Juventud Antoniana 50% / Tucuman Central 50%.","key_factors":["xG: Juventud Antoniana 0.00 — Tucuman Central 0.00","Posedovanje: 50% — 50%","Šutevi na gol: 0 — 0","Momentum: Juventud Antoniana 50% / Tucuman Central 50%","Preostalo: 45 min"],"stats_breakdown":{"momentum_home":0.5,"momentum_away":0.5,"xg_home":0.0,"xg_away":0.0,"all_markets":{"Domaćin pobeđuje [1-0]":35,"Remi [1-0]":37,"Gost pobeđuje [1-0]":27,"Over 1.5 golova":71}}}},{"id":"fs_j3qRS77D","source":"flashscore","league":"Football","league_url":null,"home_team":"Argentino MM","away_team":"Biblioteca Atenas","kickoff":null,"status":"live","minute":37,"score":{"home":0,"away":0},"match_url":"https://www.flashscore.com/match/j3qRS77D/","tip":{"market":"Over 0.5 golova","confidence":77,"stars":4,"explanation":"Rezultat 0-0 u 37'. min, ostalo 53 min. Biblioteca Atenas dominira — posedovanje 50%, šutevi na gol 0. xG: 0.00-0.00. Momentum: Argentino MM 50% / Biblioteca Atenas 50%.","key_factors":["xG: Argentino MM 0.00 — Biblioteca Atenas 0.00","Posedovanje: 50% — 50%","Šutevi na gol: 0 — 0","Momentum: Argentino MM 50% / Biblioteca Atenas 50%","Preostalo: 53 min"],"stats_breakdown":{"momentum_home":0.5,"momentum_away":0.5,"xg_home":0.0,"xg_away":0.0,"all_markets":{"Domaćin pobeđuje [0-0]":32,"Remi [0-0]":37,"Gost pobeđuje [0-0]":32,"Over 0.5 golova":77}}}},{"id":"fs_tvy1rPVQ","source":"flashscore","league":"Football","league_url":null,"home_team":"Sarmiento de La Banda","away_team":"San Martin Formosa","kickoff":null,"status":"live","minute":26,"score":{"home":0,"away":0},"match_url":"https://www.flashscore.com/match/tvy1rPVQ/","tip":{"market":"Over 0.5 golova","confidence":83,"stars":4,"explanation":"Rezultat 0-0 u 26'. min, ostalo 64 min. San Martin Formosa dominira — posedovanje 50%, šutevi na gol 0. xG: 0.00-0.00. Momentum: Sarmiento de La Banda 50% / San Martin Formosa 50%.","key_factors":["xG: Sarmiento de La Banda 0.00 — San Martin Formosa 0.00","Posedovanje: 50% — 50%","Šutevi na gol: 0 — 0","Momentum: Sarmiento de La Banda 50% / San Martin Formosa 50%","Preostalo: 64 min"],"stats_breakdown":{"momentum_home":0.5,"momentum_away":0.5,"xg_home":0.0,"xg_away":0.0,"all_markets":{"Domaćin pobeđuje [0-0]":34,"Remi [0-0]":33,"Gost pobeđuje [0-0]":34,"Over 0.5 golova":83}}}},{"id":"fs_ddEqTC7l","source":"flashscore","league":"Football","league_url":null,"home_team":"Ind. Rivadavia","away_team":"Tigre","kickoff":null,"status":"live","minute":14,"score":{"home":0,"away":0},"match_url":"https://www.flashscore.com/match/ddEqTC7l/","tip":{"market":"Over 0.5 golova","confidence":88,"stars":4,"explanation":"Rezultat 0-0 u 14'. min, ostalo 76 min. Tigre dominira — posedovanje 50%, šutevi na gol 0. xG: 0.00-0.00. Momentum: Ind. Rivadavia 50% / Tigre 50%.","key_factors":["xG: Ind. Rivadavia 0.00 — Tigre 0.00","Posedovanje: 50% — 50%","Šutevi na gol: 0 — 0","Momentum: Ind. Rivadavia 50% / Tigre 50%","Preostalo: 76 min"],"stats_breakdown":{"momentum_home":0.5,"momentum_away":0.5,"xg_home":0.0,"xg_away":0.0,"all_markets":{"Domaćin pobeđuje [0-0]":35,"Remi [0-0]":30,"Gost pobeđuje [0-0]":35,"Over 0.5 golova":88}}}},{"id":"fs_Wjdw99Ei","source":"flashscore","league":"Football","league_url":null,"home_team":"Real Potosi","away_team":"Nacional Potosi","kickoff":null,"status":"live","minute":28,"score":{"home":0,"away":0},"match_url":"https://www.flashscore.com/match/Wjdw99Ei/","tip":{"market":"Over 0.5 golova","confidence":82,"stars":4,"explanation":"Rezultat 0-0 u 28'. min, ostalo 62 min. Nacional Potosi dominira — posedovanje 50%, šutevi na gol 0. xG: 0.00-0.00. Momentum: Real Potosi 50% / Nacional Potosi 50%.","key_factors":["xG: Real Potosi 0.00 — Nacional Potosi 0.00","Posedovanje: 50% — 50%","Šutevi na gol: 0 — 0","Momentum: Real Potosi 50% / Nacional Potosi 50%","Preostalo: 62 min"],"stats_breakdown":{"momentum_home":0.5,"momentum_away":0.5,"xg_home":0.0,"xg_away":0.0,"all_markets":{"Domaćin pobeđuje [0-0]":33,"Remi [0-0]":34,"Gost pobeđuje [0-0]":33,"Over 0.5 golova":82}}}},{"id":"fs_n5RF3TEa","source":"flashscore","league":"Football","league_url":null,"home_team":"Avai","away_team":"Nautico","kickoff":null,"status":"live","minute":27,"score":{"home":1,"away":0},"match_url":"https://www.flashscore.com/match/n5RF3TEa/","tip":{"market":"Over 1.5 golova","confidence":83,"stars":4,"explanation":"Rezultat 1-0 u 27'. min, ostalo 63 min. Nautico dominira — posedovanje 50%, šutevi na gol 0. xG: 0.00-0.00. Momentum: Avai 50% / Nautico 50%.","key_factors":["xG: Avai 0.00 — Nautico 0.00","Posedovanje: 50% — 50%","Šutevi na gol: 0 — 0","Momentum: Avai 50% / Nautico 50%","Preostalo: 63 min"],"stats_breakdown":{"momentum_home":0.5,"momentum_away":0.5,"xg_home":0.0,"xg_away":0.0,"all_markets":{"Domaćin pobeđuje [1-0]":39,"Remi [1-0]":30,"Gost pobeđuje [1-0]":30,"Over 1.5 golova":83}}}},{"id":"fs_xhqzijVg","source":"flashscore","league":"Football","league_url":null,"home_team":"Sao Bernardo","away_team":"Cuiaba","kickoff":null,"status":"live","minute":30,"score":{"home":1,"away":2},"match_url":"https://www.flashscore.com/match/xhqzijVg/","tip":{"market":"Over 3.5 golova","confidence":81,"stars":4,"explanation":"Rezultat 1-2 u 30'. min, ostalo 60 min. Cuiaba dominira — posedovanje 50%, šutevi na gol 0. xG: 0.00-0.00. Momentum: Sao Bernardo 50% / Cuiaba 50%.","key_factors":["xG: Sao Bernardo 0.00 — Cuiaba 0.00","Posedovanje: 50% — 50%","Šutevi na gol: 0 — 0","Momentum: Sao Bernardo 50% / Cuiaba 50%","Preostalo: 60 min"],"stats_breakdown":{"momentum_home":0.5,"momentum_away":0.5,"xg_home":0.0,"xg_away":0.0,"all_markets":{"Domaćin pobeđuje [1-2]":30,"Remi [1-2]":31,"Gost pobeđuje [1-2]":39,"Over 3.5 golova":81}}}},{"id":"fs_MV1UKXRh","source":"flashscore","league":"Football","league_url":null,"home_team":"Atletico Colina","away_team":"Real San Joaquin","kickoff":null,"status":"live","minute":1,"score":{"home":0,"away":0},"match_url":"https://www.flashscore.com/match/MV1UKXRh/","tip":{"market":"Over 0.5 golova","confidence":92,"stars":5,"explanation":"Rezultat 0-0 u 1'. min, ostalo 89 min. Real San Joaquin dominira — posedovanje 50%, šutevi na gol 0. xG: 0.00-0.00. Momentum: Atletico Colina 50% / Real San Joaquin 50%.","key_factors":["xG: Atletico Colina 0.00 — Real San Joaquin 0.00","Posedovanje: 50% — 50%","Šutevi na gol: 0 — 0","Momentum: Atletico Colina 50% / Real San Joaquin 50%","Preostalo: 89 min"],"stats_breakdown":{"momentum_home":0.5,"momentum_away":0.5,"xg_home":0.0,"xg_away":0.0,"all_markets":{"Domaćin pobeđuje [0-0]":36,"Remi [0-0]":27,"Gost pobeđuje [0-0]":36,"Over 0.5 golova":92}}}},{"id":"fs_pKiS3Ry3","source":"flashscore","league":"Football","league_url":null,"home_team":"Lota Schwager","away_team":"Osorno","kickoff":null,"status":"live","minute":3,"score":{"home":0,"away":0},"match_url":"https://www.flashscore.com/match/pKiS3Ry3/","tip":{"market":"Over 0.5 golova","confidence":91,"stars":5,"explanation":"Rezultat 0-0 u 3'. min, ostalo 87 min. Osorno dominira — posedovanje 50%, šutevi na gol 0. xG: 0.00-0.00. Momentum: Lota Schwager 50% / Osorno 50%.","key_factors":["xG: Lota Schwager 0.00 — Osorno 0.00","Posedovanje: 50% — 50%","Šutevi na gol: 0 — 0","Momentum: Lota Schwager 50% / Osorno 50%","Preostalo: 87 min"],"stats_breakdown":{"momentum_home":0.5,"momentum_away":0.5,"xg_home":0.0,"xg_away":0.0,"all_markets":{"Domaćin pobeđuje [0-0]":36,"Remi [0-0]":27,"Gost pobeđuje [0-0]":36,"Over 0.5 golova":91}}}},{"id":"fs_KMD2Ge5e","source":"flashscore","league":"Football","league_url":null,"home_team":"Coquimbo","away_team":"Union La Calera","kickoff":null,"status":"live","minute":27,"score":{"home":0,"away":0},"match_url":"https://www.flashscore.com/match/KMD2Ge5e/","tip":{"market":"Over 0.5 golova","confidence":83,"stars":4,"explanation":"Rezultat 0-0 u 27'. min, ostalo 63 min. Union La Calera dominira — posedovanje 50%, šutevi na gol 0. xG: 0.00-0.00. Momentum: Coquimbo 50% / Union La Calera 50%.","key_factors":["xG: Coquimbo 0.00 — Union La Calera 0.00","Posedovanje: 50% — 50%","Šutevi na gol: 0 — 0","Momentum: Coquimbo 50% / Union La Calera 50%","Preostalo: 63 min"],"stats_breakdown":{"momentum_home":0.5,"momentum_away":0.5,"xg_home":0.0,"xg_away":0.0,"all_markets":{"Domaćin pobeđuje [0-0]":33,"Remi [0-0]":33,"Gost pobeđuje [0-0]":33,"Over 0.5 golova":83}}}},{"id":"fs_OWDMXPhm","source":"flashscore","league":"Football","league_url":null,"home_team":"Dep. Cuenca","away_team":"Aucas","kickoff":null,"status":"live","minute":13,"score":{"home":0,"away":1},"match_url":"https://www.flashscore.com/match/OWDMXPhm/","tip":{"market":"Over 1.5 golova","confidence":88,"stars":4,"explanation":"Rezultat 0-1 u 13'. min, ostalo 77 min. Aucas dominira — posedovanje 50%, šutevi na gol 0. xG: 0.00-0.00. Momentum: Dep. Cuenca 50% / Aucas 50%.","key_factors":["xG: Dep. Cuenca 0.00 — Aucas 0.00","Posedovanje: 50% — 50%","Šutevi na gol: 0 — 0","Momentum: Dep. Cuenca 50% / Aucas 50%","Preostalo: 77 min"],"stats_breakdown":{"momentum_home":0.5,"momentum_away":0.5,"xg_home":0.0,"xg_away":0.0,"all_markets":{"Domaćin pobeđuje [0-1]":32,"Remi [0-1]":27,"Gost pobeđuje [0-1]":41,"Over 1.5 golova":88}}}},{"id":"fs_MmjeHJwq","source":"flashscore","league":"Football","league_url":null,"home_team":"Fram","away_team":"Thor Akureyri","kickoff":null,"status":"live","minute":74,"score":{"home":5,"away":1},"match_url":"https://www.flashscore.com/match/MmjeHJwq/","tip":{"market":"Remi [5-1]","confidence":63,"stars":3,"explanation":"Rezultat 5-1 u 74'. min, ostalo 16 min. Thor Akureyri dominira — posedovanje 50%, šutevi na gol 0. xG: 0.00-0.00. Momentum: Fram 50% / Thor Akureyri 50%.","key_factors":["xG: Fram 0.00 — Thor Akureyri 0.00","Posedovanje: 50% — 50%","Šutevi na gol: 0 — 0","Momentum: Fram 50% / Thor Akureyri 50%","Preostalo: 16 min"],"stats_breakdown":{"momentum_home":0.5,"momentum_away":0.5,"xg_home":0.0,"xg_away":0.0,"all_markets":{"Domaćin pobeđuje [5-1]":21,"Remi [5-1]":63,"Gost pobeđuje [5-1]":16,"Over 6.5 golova":36}}}},{"id":"fs_j5aPMuGL","source":"flashscore","league":"Football","league_url":null,"home_team":"KA Akureyri","away_team":"Akranes","kickoff":null,"status":"live","minute":73,"score":{"home":2,"away":2},"match_url":"https://www.flashscore.com/match/j5aPMuGL/","tip":{"market":"Remi [2-2]","confidence":65,"stars":3,"explanation":"Rezultat 2-2 u 73'. min, ostalo 17 min. Akranes dominira — posedovanje 50%, šutevi na gol 0. xG: 0.00-0.00. Momentum: KA Akureyri 50% / Akranes 50%.","key_factors":["xG: KA Akureyri 0.00 — Akranes 0.00","Posedovanje: 50% — 50%","Šutevi na gol: 0 — 0","Momentum: KA Akureyri 50% / Akranes 50%","Preostalo: 17 min"],"stats_breakdown":{"momentum_home":0.5,"momentum_away":0.5,"xg_home":0.0,"xg_away":0.0,"all_markets":{"Domaćin pobeđuje [2-2]":18,"Remi [2-2]":65,"Gost pobeđuje [2-2]":18,"Over 4.5 golova":38}}}},{"id":"fs_2cb3Fc8e","source":"flashscore","league":"Football","league_url":null,"home_team":"KR Reykjavik","away_team":"Vestmannaeyjar","kickoff":null,"status":"live","minute":69,"score":{"home":5,"away":1},"match_url":"https://www.flashscore.com/match/2cb3Fc8e/","tip":{"market":"Remi [5-1]","confidence":56,"stars":3,"explanation":"Rezultat 5-1 u 69'. min, ostalo 21 min. Vestmannaeyjar dominira — posedovanje 50%, šutevi na gol 0. xG: 0.00-0.00. Momentum: KR Reykjavik 50% / Vestmannaeyjar 50%.","key_factors":["xG: KR Reykjavik 0.00 — Vestmannaeyjar 0.00","Posedovanje: 50% — 50%","Šutevi na gol: 0 — 0","Momentum: KR Reykjavik 50% / Vestmannaeyjar 50%","Preostalo: 21 min"],"stats_breakdown":{"momentum_home":0.5,"momentum_away":0.5,"xg_home":0.0,"xg_away":0.0,"all_markets":{"Domaćin pobeđuje [5-1]":25,"Remi [5-1]":56,"Gost pobeđuje [5-1]":19,"Over 6.5 golova":44}}}},{"id":"fs_OKVRzD65","source":"flashscore","league":"Football","league_url":null,"home_team":"Jwayya","away_team":"Nejmeh SC","kickoff":null,"status":"live","minute":66,"score":{"home":0,"away":0},"match_url":"https://www.flashscore.com/match/OKVRzD65/","tip":{"market":"Remi [0-0]","confidence":56,"stars":3,"explanation":"Rezultat 0-0 u 66'. min, ostalo 24 min. Nejmeh SC dominira — posedovanje 50%, šutevi na gol 0. xG: 0.00-0.00. Momentum: Jwayya 50% / Nejmeh SC 50%.","key_factors":["xG: Jwayya 0.00 — Nejmeh SC 0.00","Posedovanje: 50% — 50%","Šutevi na gol: 0 — 0","Momentum: Jwayya 50% / Nejmeh SC 50%","Preostalo: 24 min"],"stats_breakdown":{"momentum_home":0.5,"momentum_away":0.5,"xg_home":0.0,"xg_away":0.0,"all_markets":{"Domaćin pobeđuje [0-0]":22,"Remi [0-0]":56,"Gost pobeđuje [0-0]":22,"Over 0.5 golova":49}}}},{"id":"fs_jLAEetno","source":"flashscore","league":"Football","league_url":null,"home_team":"Moquegua","away_team":"Deportivo Garcilaso","kickoff":null,"status":"live","minute":69,"score":{"home":0,"away":0},"match_url":"https://www.flashscore.com/match/jLAEetno/","tip":{"market":"Remi [0-0]","confidence":60,"stars":3,"explanation":"Rezultat 0-0 u 69'. min, ostalo 21 min. Deportivo Garcilaso dominira — posedovanje 50%, šutevi na gol 0. xG: 0.00-0.00. Momentum: Moquegua 50% / Deportivo Garcilaso 50%.","key_factors":["xG: Moquegua 0.00 — Deportivo Garcilaso 0.00","Posedovanje: 50% — 50%","Šutevi na gol: 0 — 0","Momentum: Moquegua 50% / Deportivo Garcilaso 50%","Preostalo: 21 min"],"stats_breakdown":{"momentum_home":0.5,"momentum_away":0.5,"xg_home":0.0,"xg_away":0.0,"all_markets":{"Domaćin pobeđuje [0-0]":20,"Remi [0-0]":60,"Gost pobeđuje [0-0]":20,"Over 0.5 golova":44}}}},{"id":"fs_AoZmkBmn","source":"flashscore","league":"Football","league_url":null,"home_team":"Univ. Craiova","away_team":"U. Cluj","kickoff":null,"status":"live","minute":null,"score":{"home":1,"away":1},"match_url":"https://www.flashscore.com/match/AoZmkBmn/","tip":{"market":"Over 2.5 golova","confidence":71,"stars":4,"explanation":"Rezultat 1-1 u 45'. min, ostalo 45 min. U. Cluj dominira — posedovanje 50%, šutevi na gol 0. xG: 0.00-0.00. Momentum: Univ. Craiova 50% / U. Cluj 50%.","key_factors":["xG: Univ. Craiova 0.00 — U. Cluj 0.00","Posedovanje: 50% — 50%","Šutevi na gol: 0 — 0","Momentum: Univ. Craiova 50% / U. Cluj 50%","Preostalo: 45 min"],"stats_breakdown":{"momentum_home":0.5,"momentum_away":0.5,"xg_home":0.0,"xg_away":0.0,"all_markets":{"Domaćin pobeđuje [1-1]":30,"Remi [1-1]":41,"Gost pobeđuje [1-1]":30,"Over 2.5 golova":71}}}}],"last_updated":"19:29"}