{"matches":[{"id":"fs_G4HJIIa3","source":"flashscore","league":"Football","league_url":null,"home_team":"Naftan","away_team":"Dynamo Brest","kickoff":null,"status":"live","minute":null,"score":{"home":2,"away":3},"match_url":"https://www.flashscore.com/match/G4HJIIa3/","tip":{"market":"Over 5.5 golova","confidence":71,"stars":4,"explanation":"Rezultat 2-3 u 45'. min, ostalo 45 min. Dynamo Brest dominira — posedovanje 50%, šutevi na gol 0. xG: 0.00-0.00. Momentum: Naftan 50% / Dynamo Brest 50%.","key_factors":["xG: Naftan 0.00 — Dynamo Brest 0.00","Posedovanje: 50% — 50%","Šutevi na gol: 0 — 0","Momentum: Naftan 50% / Dynamo Brest 50%","Preostalo: 45 min"],"stats_breakdown":{"momentum_home":0.5,"momentum_away":0.5,"xg_home":0.0,"xg_away":0.0,"all_markets":{"Domaćin pobeđuje [2-3]":27,"Remi [2-3]":37,"Gost pobeđuje [2-3]":35,"Over 5.5 golova":71}}}},{"id":"fs_fcajfg6e","source":"flashscore","league":"Football","league_url":null,"home_team":"Minsk 2","away_team":"FC Gomel 2","kickoff":null,"status":"live","minute":90,"score":{"home":0,"away":2},"match_url":"https://www.flashscore.com/match/fcajfg6e/","tip":{"market":"Remi [0-2]","confidence":98,"stars":5,"explanation":"Rezultat 0-2 u 90'. min, ostalo 0 min. FC Gomel 2 dominira — posedovanje 50%, šutevi na gol 0. xG: 0.00-0.00. Momentum: Minsk 2 50% / FC Gomel 2 50%.","key_factors":["xG: Minsk 2 0.00 — FC Gomel 2 0.00","Posedovanje: 50% — 50%","Šutevi na gol: 0 — 0","Momentum: Minsk 2 50% / FC Gomel 2 50%","Preostalo: 0 min"],"stats_breakdown":{"momentum_home":0.5,"momentum_away":0.5,"xg_home":0.0,"xg_away":0.0,"all_markets":{"Domaćin pobeđuje [0-2]":1,"Remi [0-2]":98,"Gost pobeđuje [0-2]":1,"Over 2.5 golova":0}}}},{"id":"fs_UkvsSlYo","source":"flashscore","league":"Football","league_url":null,"home_team":"Yunnan Yukun","away_team":"Henan Songshan Longmen","kickoff":null,"status":"live","minute":83,"score":{"home":2,"away":1},"match_url":"https://www.flashscore.com/match/UkvsSlYo/","tip":{"market":"Remi [2-1]","confidence":79,"stars":4,"explanation":"Rezultat 2-1 u 83'. min, ostalo 7 min. Henan Songshan Longmen dominira — posedovanje 50%, šutevi na gol 0. xG: 0.00-0.00. Momentum: Yunnan Yukun 50% / Henan Songshan Longmen 50%.","key_factors":["xG: Yunnan Yukun 0.00 — Henan Songshan Longmen 0.00","Posedovanje: 50% — 50%","Šutevi na gol: 0 — 0","Momentum: Yunnan Yukun 50% / Henan Songshan Longmen 50%","Preostalo: 7 min"],"stats_breakdown":{"momentum_home":0.5,"momentum_away":0.5,"xg_home":0.0,"xg_away":0.0,"all_markets":{"Domaćin pobeđuje [2-1]":12,"Remi [2-1]":79,"Gost pobeđuje [2-1]":9,"Over 3.5 golova":18}}}},{"id":"fs_ll6h3uiI","source":"flashscore","league":"Football","league_url":null,"home_team":"Mechal","away_team":"Hadiya Hossana","kickoff":null,"status":"live","minute":null,"score":{"home":0,"away":0},"match_url":"https://www.flashscore.com/match/ll6h3uiI/","tip":{"market":"Over 0.5 golova","confidence":71,"stars":4,"explanation":"Rezultat 0-0 u 45'. min, ostalo 45 min. Hadiya Hossana dominira — posedovanje 50%, šutevi na gol 0. xG: 0.00-0.00. Momentum: Mechal 50% / Hadiya Hossana 50%.","key_factors":["xG: Mechal 0.00 — Hadiya Hossana 0.00","Posedovanje: 50% — 50%","Šutevi na gol: 0 — 0","Momentum: Mechal 50% / Hadiya Hossana 50%","Preostalo: 45 min"],"stats_breakdown":{"momentum_home":0.5,"momentum_away":0.5,"xg_home":0.0,"xg_away":0.0,"all_markets":{"Domaćin pobeđuje [0-0]":30,"Remi [0-0]":41,"Gost pobeđuje [0-0]":30,"Over 0.5 golova":71}}}},{"id":"fs_jH5JwaOH","source":"flashscore","league":"Football","league_url":null,"home_team":"Tadamon","away_team":"Al Ansar","kickoff":null,"status":"live","minute":55,"score":{"home":0,"away":1},"match_url":"https://www.flashscore.com/match/jH5JwaOH/","tip":{"market":"Over 1.5 golova","confidence":62,"stars":3,"explanation":"Rezultat 0-1 u 55'. min, ostalo 35 min. Al Ansar dominira — posedovanje 50%, šutevi na gol 0. xG: 0.00-0.00. Momentum: Tadamon 50% / Al Ansar 50%.","key_factors":["xG: Tadamon 0.00 — Al Ansar 0.00","Posedovanje: 50% — 50%","Šutevi na gol: 0 — 0","Momentum: Tadamon 50% / Al Ansar 50%","Preostalo: 35 min"],"stats_breakdown":{"momentum_home":0.5,"momentum_away":0.5,"xg_home":0.0,"xg_away":0.0,"all_markets":{"Domaćin pobeđuje [0-1]":25,"Remi [0-1]":43,"Gost pobeđuje [0-1]":32,"Over 1.5 golova":62}}}},{"id":"fs_GOoDJlS6","source":"flashscore","league":"Football","league_url":null,"home_team":"Shao Jiang","away_team":"Artilheiros","kickoff":null,"status":"live","minute":null,"score":{"home":7,"away":0},"match_url":"https://www.flashscore.com/match/GOoDJlS6/","tip":{"market":"Over 7.5 golova","confidence":71,"stars":4,"explanation":"Rezultat 7-0 u 45'. min, ostalo 45 min. Artilheiros dominira — posedovanje 50%, šutevi na gol 0. xG: 0.00-0.00. Momentum: Shao Jiang 50% / Artilheiros 50%.","key_factors":["xG: Shao Jiang 0.00 — Artilheiros 0.00","Posedovanje: 50% — 50%","Šutevi na gol: 0 — 0","Momentum: Shao Jiang 50% / Artilheiros 50%","Preostalo: 45 min"],"stats_breakdown":{"momentum_home":0.5,"momentum_away":0.5,"xg_home":0.0,"xg_away":0.0,"all_markets":{"Domaćin pobeđuje [7-0]":35,"Remi [7-0]":37,"Gost pobeđuje [7-0]":27,"Over 7.5 golova":71}}}},{"id":"fs_Y7UkmEsg","source":"flashscore","league":"Football","league_url":null,"home_team":"Brann (Nor)","away_team":"Kristiansund (Nor)","kickoff":null,"status":"live","minute":null,"score":{"home":0,"away":1},"match_url":"https://www.flashscore.com/match/Y7UkmEsg/","tip":{"market":"Over 1.5 golova","confidence":71,"stars":4,"explanation":"Rezultat 0-1 u 45'. min, ostalo 45 min. Kristiansund (Nor) dominira — posedovanje 50%, šutevi na gol 0. xG: 0.00-0.00. Momentum: Brann (Nor) 50% / Kristiansund (Nor) 50%.","key_factors":["xG: Brann (Nor) 0.00 — Kristiansund (Nor) 0.00","Posedovanje: 50% — 50%","Šutevi na gol: 0 — 0","Momentum: Brann (Nor) 50% / Kristiansund (Nor) 50%","Preostalo: 45 min"],"stats_breakdown":{"momentum_home":0.5,"momentum_away":0.5,"xg_home":0.0,"xg_away":0.0,"all_markets":{"Domaćin pobeđuje [0-1]":27,"Remi [0-1]":37,"Gost pobeđuje [0-1]":35,"Over 1.5 golova":71}}}},{"id":"fs_A7A5DXld","source":"flashscore","league":"Football","league_url":null,"home_team":"Sturm Graz II (Aut)","away_team":"Honved (Hun)","kickoff":null,"status":"live","minute":17,"score":{"home":0,"away":0},"match_url":"https://www.flashscore.com/match/A7A5DXld/","tip":{"market":"Over 0.5 golova","confidence":87,"stars":4,"explanation":"Rezultat 0-0 u 17'. min, ostalo 73 min. Honved (Hun) dominira — posedovanje 50%, šutevi na gol 0. xG: 0.00-0.00. Momentum: Sturm Graz II (Aut) 50% / Honved (Hun) 50%.","key_factors":["xG: Sturm Graz II (Aut) 0.00 — Honved (Hun) 0.00","Posedovanje: 50% — 50%","Šutevi na gol: 0 — 0","Momentum: Sturm Graz II (Aut) 50% / Honved (Hun) 50%","Preostalo: 73 min"],"stats_breakdown":{"momentum_home":0.5,"momentum_away":0.5,"xg_home":0.0,"xg_away":0.0,"all_markets":{"Domaćin pobeđuje [0-0]":35,"Remi [0-0]":30,"Gost pobeđuje [0-0]":35,"Over 0.5 golova":87}}}}],"last_updated":"13:51"}