{"matches":[{"id":"fs_r9zn5H2k","source":"flashscore","league":"Football","league_url":null,"home_team":"Austria U19 W","away_team":"Iceland U19 W","kickoff":null,"status":"live","minute":89,"score":{"home":2,"away":0},"match_url":"https://www.flashscore.com/match/r9zn5H2k/","tip":{"market":"Remi [2-0]","confidence":95,"stars":5,"explanation":"Rezultat 2-0 u 89'. min, ostalo 1 min. Iceland U19 W dominira — posedovanje 50%, šutevi na gol 0. xG: 0.00-0.00. Momentum: Austria U19 W 50% / Iceland U19 W 50%.","key_factors":["xG: Austria U19 W 0.00 — Iceland U19 W 0.00","Posedovanje: 50% — 50%","Šutevi na gol: 0 — 0","Momentum: Austria U19 W 50% / Iceland U19 W 50%","Preostalo: 1 min"],"stats_breakdown":{"momentum_home":0.5,"momentum_away":0.5,"xg_home":0.0,"xg_away":0.0,"all_markets":{"Domaćin pobeđuje [2-0]":3,"Remi [2-0]":95,"Gost pobeđuje [2-0]":2,"Over 2.5 golova":3}}}},{"id":"fs_bRohrxOj","source":"flashscore","league":"Football","league_url":null,"home_team":"Dnepr Mogilev","away_team":"Neman","kickoff":null,"status":"live","minute":90,"score":{"home":2,"away":0},"match_url":"https://www.flashscore.com/match/bRohrxOj/","tip":{"market":"Remi [2-0]","confidence":98,"stars":5,"explanation":"Rezultat 2-0 u 90'. min, ostalo 0 min. Neman dominira — posedovanje 50%, šutevi na gol 0. xG: 0.00-0.00. Momentum: Dnepr Mogilev 50% / Neman 50%.","key_factors":["xG: Dnepr Mogilev 0.00 — Neman 0.00","Posedovanje: 50% — 50%","Šutevi na gol: 0 — 0","Momentum: Dnepr Mogilev 50% / Neman 50%","Preostalo: 0 min"],"stats_breakdown":{"momentum_home":0.5,"momentum_away":0.5,"xg_home":0.0,"xg_away":0.0,"all_markets":{"Domaćin pobeđuje [2-0]":1,"Remi [2-0]":98,"Gost pobeđuje [2-0]":1,"Over 2.5 golova":0}}}},{"id":"fs_l0lDVbvo","source":"flashscore","league":"Football","league_url":null,"home_team":"Isloch","away_team":"Belshina","kickoff":null,"status":"live","minute":64,"score":{"home":4,"away":0},"match_url":"https://www.flashscore.com/match/l0lDVbvo/","tip":{"market":"Remi [4-0]","confidence":51,"stars":3,"explanation":"Rezultat 4-0 u 64'. min, ostalo 26 min. Belshina dominira — posedovanje 50%, šutevi na gol 0. xG: 0.00-0.00. Momentum: Isloch 50% / Belshina 50%.","key_factors":["xG: Isloch 0.00 — Belshina 0.00","Posedovanje: 50% — 50%","Šutevi na gol: 0 — 0","Momentum: Isloch 50% / Belshina 50%","Preostalo: 26 min"],"stats_breakdown":{"momentum_home":0.5,"momentum_away":0.5,"xg_home":0.0,"xg_away":0.0,"all_markets":{"Domaćin pobeđuje [4-0]":28,"Remi [4-0]":51,"Gost pobeđuje [4-0]":21,"Over 4.5 golova":51}}}},{"id":"fs_6aoxt3oo","source":"flashscore","league":"Football","league_url":null,"home_team":"BATE 2","away_team":"SKA-1938","kickoff":null,"status":"live","minute":90,"score":{"home":3,"away":4},"match_url":"https://www.flashscore.com/match/6aoxt3oo/","tip":{"market":"Remi [3-4]","confidence":98,"stars":5,"explanation":"Rezultat 3-4 u 90'. min, ostalo 0 min. SKA-1938 dominira — posedovanje 50%, šutevi na gol 0. xG: 0.00-0.00. Momentum: BATE 2 50% / SKA-1938 50%.","key_factors":["xG: BATE 2 0.00 — SKA-1938 0.00","Posedovanje: 50% — 50%","Šutevi na gol: 0 — 0","Momentum: BATE 2 50% / SKA-1938 50%","Preostalo: 0 min"],"stats_breakdown":{"momentum_home":0.5,"momentum_away":0.5,"xg_home":0.0,"xg_away":0.0,"all_markets":{"Domaćin pobeđuje [3-4]":1,"Remi [3-4]":98,"Gost pobeđuje [3-4]":1,"Over 7.5 golova":0}}}},{"id":"fs_l4cJT3ml","source":"flashscore","league":"Football","league_url":null,"home_team":"Bafang","away_team":"Dynamo Douala","kickoff":null,"status":"live","minute":90,"score":{"home":2,"away":7},"match_url":"https://www.flashscore.com/match/l4cJT3ml/","tip":{"market":"Remi [2-7]","confidence":98,"stars":5,"explanation":"Rezultat 2-7 u 90'. min, ostalo 0 min. Dynamo Douala dominira — posedovanje 50%, šutevi na gol 0. xG: 0.00-0.00. Momentum: Bafang 50% / Dynamo Douala 50%.","key_factors":["xG: Bafang 0.00 — Dynamo Douala 0.00","Posedovanje: 50% — 50%","Šutevi na gol: 0 — 0","Momentum: Bafang 50% / Dynamo Douala 50%","Preostalo: 0 min"],"stats_breakdown":{"momentum_home":0.5,"momentum_away":0.5,"xg_home":0.0,"xg_away":0.0,"all_markets":{"Domaćin pobeđuje [2-7]":1,"Remi [2-7]":98,"Gost pobeđuje [2-7]":1,"Over 9.5 golova":0}}}},{"id":"fs_IwPAMBph","source":"flashscore","league":"Football","league_url":null,"home_team":"Cobresal","away_team":"Antofagasta","kickoff":null,"status":"live","minute":22,"score":{"home":0,"away":1},"match_url":"https://www.flashscore.com/match/IwPAMBph/","tip":{"market":"Over 1.5 golova","confidence":85,"stars":4,"explanation":"Rezultat 0-1 u 22'. min, ostalo 68 min. Antofagasta dominira — posedovanje 50%, šutevi na gol 0. xG: 0.00-0.00. Momentum: Cobresal 50% / Antofagasta 50%.","key_factors":["xG: Cobresal 0.00 — Antofagasta 0.00","Posedovanje: 50% — 50%","Šutevi na gol: 0 — 0","Momentum: Cobresal 50% / Antofagasta 50%","Preostalo: 68 min"],"stats_breakdown":{"momentum_home":0.5,"momentum_away":0.5,"xg_home":0.0,"xg_away":0.0,"all_markets":{"Domaćin pobeđuje [0-1]":31,"Remi [0-1]":29,"Gost pobeđuje [0-1]":40,"Over 1.5 golova":85}}}},{"id":"fs_QVMPb8ho","source":"flashscore","league":"Football","league_url":null,"home_team":"La Serena","away_team":"Cobreloa","kickoff":null,"status":"live","minute":21,"score":{"home":0,"away":0},"match_url":"https://www.flashscore.com/match/QVMPb8ho/","tip":{"market":"Over 0.5 golova","confidence":85,"stars":4,"explanation":"Rezultat 0-0 u 21'. min, ostalo 69 min. Cobreloa dominira — posedovanje 50%, šutevi na gol 0. xG: 0.00-0.00. Momentum: La Serena 50% / Cobreloa 50%.","key_factors":["xG: La Serena 0.00 — Cobreloa 0.00","Posedovanje: 50% — 50%","Šutevi na gol: 0 — 0","Momentum: La Serena 50% / Cobreloa 50%","Preostalo: 69 min"],"stats_breakdown":{"momentum_home":0.5,"momentum_away":0.5,"xg_home":0.0,"xg_away":0.0,"all_markets":{"Domaćin pobeđuje [0-0]":34,"Remi [0-0]":31,"Gost pobeđuje [0-0]":34,"Over 0.5 golova":85}}}},{"id":"fs_As4mmSvq","source":"flashscore","league":"Football","league_url":null,"home_team":"Levadia","away_team":"Flora","kickoff":null,"status":"live","minute":null,"score":{"home":1,"away":0},"match_url":"https://www.flashscore.com/match/As4mmSvq/","tip":{"market":"Over 1.5 golova","confidence":71,"stars":4,"explanation":"Rezultat 1-0 u 45'. min, ostalo 45 min. Flora dominira — posedovanje 50%, šutevi na gol 0. xG: 0.00-0.00. Momentum: Levadia 50% / Flora 50%.","key_factors":["xG: Levadia 0.00 — Flora 0.00","Posedovanje: 50% — 50%","Šutevi na gol: 0 — 0","Momentum: Levadia 50% / Flora 50%","Preostalo: 45 min"],"stats_breakdown":{"momentum_home":0.5,"momentum_away":0.5,"xg_home":0.0,"xg_away":0.0,"all_markets":{"Domaćin pobeđuje [1-0]":35,"Remi [1-0]":37,"Gost pobeđuje [1-0]":27,"Over 1.5 golova":71}}}},{"id":"fs_SMmxibwo","source":"flashscore","league":"Football","league_url":null,"home_team":"OLS Oulu","away_team":"KuPS Akatemia","kickoff":null,"status":"live","minute":68,"score":{"home":2,"away":1},"match_url":"https://www.flashscore.com/match/SMmxibwo/","tip":{"market":"Remi [2-1]","confidence":55,"stars":3,"explanation":"Rezultat 2-1 u 68'. min, ostalo 22 min. KuPS Akatemia dominira — posedovanje 50%, šutevi na gol 0. xG: 0.00-0.00. Momentum: OLS Oulu 50% / KuPS Akatemia 50%.","key_factors":["xG: OLS Oulu 0.00 — KuPS Akatemia 0.00","Posedovanje: 50% — 50%","Šutevi na gol: 0 — 0","Momentum: OLS Oulu 50% / KuPS Akatemia 50%","Preostalo: 22 min"],"stats_breakdown":{"momentum_home":0.5,"momentum_away":0.5,"xg_home":0.0,"xg_away":0.0,"all_markets":{"Domaćin pobeđuje [2-1]":25,"Remi [2-1]":55,"Gost pobeđuje [2-1]":19,"Over 3.5 golova":46}}}},{"id":"fs_l6FXJFgn","source":"flashscore","league":"Football","league_url":null,"home_team":"Iecava/Olaine W","away_team":"Auda W","kickoff":null,"status":"live","minute":90,"score":{"home":2,"away":1},"match_url":"https://www.flashscore.com/match/l6FXJFgn/","tip":{"market":"Remi [2-1]","confidence":98,"stars":5,"explanation":"Rezultat 2-1 u 90'. min, ostalo 0 min. Auda W dominira — posedovanje 50%, šutevi na gol 0. xG: 0.00-0.00. Momentum: Iecava/Olaine W 50% / Auda W 50%.","key_factors":["xG: Iecava/Olaine W 0.00 — Auda W 0.00","Posedovanje: 50% — 50%","Šutevi na gol: 0 — 0","Momentum: Iecava/Olaine W 50% / Auda W 50%","Preostalo: 0 min"],"stats_breakdown":{"momentum_home":0.5,"momentum_away":0.5,"xg_home":0.0,"xg_away":0.0,"all_markets":{"Domaćin pobeđuje [2-1]":1,"Remi [2-1]":98,"Gost pobeđuje [2-1]":1,"Over 3.5 golova":0}}}},{"id":"fs_ngPeO52D","source":"flashscore","league":"Football","league_url":null,"home_team":"Banga","away_team":"Hegelmann","kickoff":null,"status":"live","minute":90,"score":{"home":1,"away":0},"match_url":"https://www.flashscore.com/match/ngPeO52D/","tip":{"market":"Remi [1-0]","confidence":98,"stars":5,"explanation":"Rezultat 1-0 u 90'. min, ostalo 0 min. Hegelmann dominira — posedovanje 50%, šutevi na gol 0. xG: 0.00-0.00. Momentum: Banga 50% / Hegelmann 50%.","key_factors":["xG: Banga 0.00 — Hegelmann 0.00","Posedovanje: 50% — 50%","Šutevi na gol: 0 — 0","Momentum: Banga 50% / Hegelmann 50%","Preostalo: 0 min"],"stats_breakdown":{"momentum_home":0.5,"momentum_away":0.5,"xg_home":0.0,"xg_away":0.0,"all_markets":{"Domaćin pobeđuje [1-0]":1,"Remi [1-0]":98,"Gost pobeđuje [1-0]":1,"Over 1.5 golova":0}}}},{"id":"fs_jNJSx5H6","source":"flashscore","league":"Football","league_url":null,"home_team":"Dziugas Telsiai","away_team":"Zalgiris","kickoff":null,"status":"live","minute":46,"score":{"home":0,"away":0},"match_url":"https://www.flashscore.com/match/jNJSx5H6/","tip":{"market":"Over 0.5 golova","confidence":71,"stars":4,"explanation":"Rezultat 0-0 u 46'. min, ostalo 44 min. Zalgiris dominira — posedovanje 50%, šutevi na gol 0. xG: 0.00-0.00. Momentum: Dziugas Telsiai 50% / Zalgiris 50%.","key_factors":["xG: Dziugas Telsiai 0.00 — Zalgiris 0.00","Posedovanje: 50% — 50%","Šutevi na gol: 0 — 0","Momentum: Dziugas Telsiai 50% / Zalgiris 50%","Preostalo: 44 min"],"stats_breakdown":{"momentum_home":0.5,"momentum_away":0.5,"xg_home":0.0,"xg_away":0.0,"all_markets":{"Domaćin pobeđuje [0-0]":29,"Remi [0-0]":41,"Gost pobeđuje [0-0]":29,"Over 0.5 golova":71}}}},{"id":"fs_Iupvh8kd","source":"flashscore","league":"Football","league_url":null,"home_team":"Sheriff Tiraspol","away_team":"Real Sireti","kickoff":null,"status":"live","minute":90,"score":{"home":3,"away":0},"match_url":"https://www.flashscore.com/match/Iupvh8kd/","tip":{"market":"Remi [3-0]","confidence":98,"stars":5,"explanation":"Rezultat 3-0 u 90'. min, ostalo 0 min. Real Sireti dominira — posedovanje 50%, šutevi na gol 0. xG: 0.00-0.00. Momentum: Sheriff Tiraspol 50% / Real Sireti 50%.","key_factors":["xG: Sheriff Tiraspol 0.00 — Real Sireti 0.00","Posedovanje: 50% — 50%","Šutevi na gol: 0 — 0","Momentum: Sheriff Tiraspol 50% / Real Sireti 50%","Preostalo: 0 min"],"stats_breakdown":{"momentum_home":0.5,"momentum_away":0.5,"xg_home":0.0,"xg_away":0.0,"all_markets":{"Domaćin pobeđuje [3-0]":1,"Remi [3-0]":98,"Gost pobeđuje [3-0]":1,"Over 3.5 golova":0}}}},{"id":"fs_UXskXtNc","source":"flashscore","league":"Football","league_url":null,"home_team":"Bo Rangers","away_team":"Diamond Stars","kickoff":null,"status":"live","minute":27,"score":{"home":0,"away":0},"match_url":"https://www.flashscore.com/match/UXskXtNc/","tip":{"market":"Over 0.5 golova","confidence":83,"stars":4,"explanation":"Rezultat 0-0 u 27'. min, ostalo 63 min. Diamond Stars dominira — posedovanje 50%, šutevi na gol 0. xG: 0.00-0.00. Momentum: Bo Rangers 50% / Diamond Stars 50%.","key_factors":["xG: Bo Rangers 0.00 — Diamond Stars 0.00","Posedovanje: 50% — 50%","Šutevi na gol: 0 — 0","Momentum: Bo Rangers 50% / Diamond Stars 50%","Preostalo: 63 min"],"stats_breakdown":{"momentum_home":0.5,"momentum_away":0.5,"xg_home":0.0,"xg_away":0.0,"all_markets":{"Domaćin pobeđuje [0-0]":33,"Remi [0-0]":33,"Gost pobeđuje [0-0]":33,"Over 0.5 golova":83}}}},{"id":"fs_YcO39NYb","source":"flashscore","league":"Football","league_url":null,"home_team":"Sandviken","away_team":"Helsingborg","kickoff":null,"status":"live","minute":90,"score":{"home":3,"away":2},"match_url":"https://www.flashscore.com/match/YcO39NYb/","tip":{"market":"Remi [3-2]","confidence":98,"stars":5,"explanation":"Rezultat 3-2 u 90'. min, ostalo 0 min. Helsingborg dominira — posedovanje 50%, šutevi na gol 0. xG: 0.00-0.00. Momentum: Sandviken 50% / Helsingborg 50%.","key_factors":["xG: Sandviken 0.00 — Helsingborg 0.00","Posedovanje: 50% — 50%","Šutevi na gol: 0 — 0","Momentum: Sandviken 50% / Helsingborg 50%","Preostalo: 0 min"],"stats_breakdown":{"momentum_home":0.5,"momentum_away":0.5,"xg_home":0.0,"xg_away":0.0,"all_markets":{"Domaćin pobeđuje [3-2]":1,"Remi [3-2]":98,"Gost pobeđuje [3-2]":1,"Over 5.5 golova":0}}}},{"id":"fs_fubh3ck5","source":"flashscore","league":"Football","league_url":null,"home_team":"Ferencvaros (Hun)","away_team":"Sabah Baku (Aze)","kickoff":null,"status":"live","minute":null,"score":{"home":1,"away":0},"match_url":"https://www.flashscore.com/match/fubh3ck5/","tip":{"market":"Over 1.5 golova","confidence":71,"stars":4,"explanation":"Rezultat 1-0 u 45'. min, ostalo 45 min. Sabah Baku (Aze) dominira — posedovanje 50%, šutevi na gol 0. xG: 0.00-0.00. Momentum: Ferencvaros (Hun) 50% / Sabah Baku (Aze) 50%.","key_factors":["xG: Ferencvaros (Hun) 0.00 — Sabah Baku (Aze) 0.00","Posedovanje: 50% — 50%","Šutevi na gol: 0 — 0","Momentum: Ferencvaros (Hun) 50% / Sabah Baku (Aze) 50%","Preostalo: 45 min"],"stats_breakdown":{"momentum_home":0.5,"momentum_away":0.5,"xg_home":0.0,"xg_away":0.0,"all_markets":{"Domaćin pobeđuje [1-0]":35,"Remi [1-0]":37,"Gost pobeđuje [1-0]":27,"Over 1.5 golova":71}}}},{"id":"fs_b1QxwK8a","source":"flashscore","league":"Football","league_url":null,"home_team":"Odra Opole (Pol)","away_team":"CSKA Sofia (Bul)","kickoff":null,"status":"live","minute":null,"score":{"home":0,"away":1},"match_url":"https://www.flashscore.com/match/b1QxwK8a/","tip":{"market":"Over 1.5 golova","confidence":71,"stars":4,"explanation":"Rezultat 0-1 u 45'. min, ostalo 45 min. CSKA Sofia (Bul) dominira — posedovanje 50%, šutevi na gol 0. xG: 0.00-0.00. Momentum: Odra Opole (Pol) 50% / CSKA Sofia (Bul) 50%.","key_factors":["xG: Odra Opole (Pol) 0.00 — CSKA Sofia (Bul) 0.00","Posedovanje: 50% — 50%","Šutevi na gol: 0 — 0","Momentum: Odra Opole (Pol) 50% / CSKA Sofia (Bul) 50%","Preostalo: 45 min"],"stats_breakdown":{"momentum_home":0.5,"momentum_away":0.5,"xg_home":0.0,"xg_away":0.0,"all_markets":{"Domaćin pobeđuje [0-1]":27,"Remi [0-1]":37,"Gost pobeđuje [0-1]":35,"Over 1.5 golova":71}}}},{"id":"fs_pjlEBm36","source":"flashscore","league":"Football","league_url":null,"home_team":"Aluminij (Slo)","away_team":"Noah (Arm)","kickoff":null,"status":"live","minute":22,"score":{"home":0,"away":1},"match_url":"https://www.flashscore.com/match/pjlEBm36/","tip":{"market":"Over 1.5 golova","confidence":85,"stars":4,"explanation":"Rezultat 0-1 u 22'. min, ostalo 68 min. Noah (Arm) dominira — posedovanje 50%, šutevi na gol 0. xG: 0.00-0.00. Momentum: Aluminij (Slo) 50% / Noah (Arm) 50%.","key_factors":["xG: Aluminij (Slo) 0.00 — Noah (Arm) 0.00","Posedovanje: 50% — 50%","Šutevi na gol: 0 — 0","Momentum: Aluminij (Slo) 50% / Noah (Arm) 50%","Preostalo: 68 min"],"stats_breakdown":{"momentum_home":0.5,"momentum_away":0.5,"xg_home":0.0,"xg_away":0.0,"all_markets":{"Domaćin pobeđuje [0-1]":31,"Remi [0-1]":29,"Gost pobeđuje [0-1]":40,"Over 1.5 golova":85}}}}],"last_updated":"16:52"}