{"matches":[{"id":"fs_jJqYR82t","source":"flashscore","league":"Football","league_url":null,"home_team":"Nacional Potosi","away_team":"Aurora","kickoff":null,"status":"live","minute":7,"score":{"home":0,"away":0},"match_url":"https://www.flashscore.com/match/jJqYR82t/","tip":{"market":"Over 0.5 golova","confidence":90,"stars":4,"explanation":"Rezultat 0-0 u 7'. min, ostalo 83 min. Aurora dominira — posedovanje 50%, šutevi na gol 0. xG: 0.00-0.00. Momentum: Nacional Potosi 50% / Aurora 50%.","key_factors":["xG: Nacional Potosi 0.00 — Aurora 0.00","Posedovanje: 50% — 50%","Šutevi na gol: 0 — 0","Momentum: Nacional Potosi 50% / Aurora 50%","Preostalo: 83 min"],"stats_breakdown":{"momentum_home":0.5,"momentum_away":0.5,"xg_home":0.0,"xg_away":0.0,"all_markets":{"Domaćin pobeđuje [0-0]":36,"Remi [0-0]":28,"Gost pobeđuje [0-0]":36,"Over 0.5 golova":90}}}},{"id":"fs_OI6HPar9","source":"flashscore","league":"Football","league_url":null,"home_team":"Nublense","away_team":"O'Higgins","kickoff":null,"status":"live","minute":null,"score":{"home":1,"away":1},"match_url":"https://www.flashscore.com/match/OI6HPar9/","tip":{"market":"Over 2.5 golova","confidence":71,"stars":4,"explanation":"Rezultat 1-1 u 45'. min, ostalo 45 min. O'Higgins dominira — posedovanje 50%, šutevi na gol 0. xG: 0.00-0.00. Momentum: Nublense 50% / O'Higgins 50%.","key_factors":["xG: Nublense 0.00 — O'Higgins 0.00","Posedovanje: 50% — 50%","Šutevi na gol: 0 — 0","Momentum: Nublense 50% / O'Higgins 50%","Preostalo: 45 min"],"stats_breakdown":{"momentum_home":0.5,"momentum_away":0.5,"xg_home":0.0,"xg_away":0.0,"all_markets":{"Domaćin pobeđuje [1-1]":30,"Remi [1-1]":41,"Gost pobeđuje [1-1]":30,"Over 2.5 golova":71}}}},{"id":"fs_zmLaytG5","source":"flashscore","league":"Football","league_url":null,"home_team":"Palmeiras W","away_team":"Paraguay W","kickoff":null,"status":"live","minute":null,"score":{"home":2,"away":0},"match_url":"https://www.flashscore.com/match/zmLaytG5/","tip":{"market":"Over 2.5 golova","confidence":71,"stars":4,"explanation":"Rezultat 2-0 u 45'. min, ostalo 45 min. Paraguay W dominira — posedovanje 50%, šutevi na gol 0. xG: 0.00-0.00. Momentum: Palmeiras W 50% / Paraguay W 50%.","key_factors":["xG: Palmeiras W 0.00 — Paraguay W 0.00","Posedovanje: 50% — 50%","Šutevi na gol: 0 — 0","Momentum: Palmeiras W 50% / Paraguay W 50%","Preostalo: 45 min"],"stats_breakdown":{"momentum_home":0.5,"momentum_away":0.5,"xg_home":0.0,"xg_away":0.0,"all_markets":{"Domaćin pobeđuje [2-0]":35,"Remi [2-0]":37,"Gost pobeđuje [2-0]":27,"Over 2.5 golova":71}}}}],"last_updated":"00:08"}