{"matches":[{"id":"fs_OW1kOMmB","source":"flashscore","league":"Football","league_url":null,"home_team":"Croatia U19","away_team":"Italy U19","kickoff":"2026-07-02T13:00:00","status":"upcoming","minute":null,"score":null,"match_url":"https://www.flashscore.com/match/OW1kOMmB/","tip":{"market":"1 — Pobeda: Croatia U19","tip_odds":3.3,"confidence":50,"stars":2,"explanation":"Croatia U19: 0pt / 0 utakmica = prosek 1.00. Italy U19: 0pt / 0 utakmica = prosek 1.00. Domaćin je jači za 0.00 boda — tip '1 — Pobeda: Croatia U19' sa 50% sigurnosti.","key_factors":[],"stats_breakdown":{"home_form_avg":1.0,"away_form_avg":1.0,"difference":0.0,"home_breakdown":[],"away_breakdown":[]}},"odds":{"home":3.3,"draw":3.25,"away":1.95}},{"id":"fs_EXYFRef3","source":"flashscore","league":"Football","league_url":null,"home_team":"Serbia U19","away_team":"Ukraine U19","kickoff":"2026-07-02T17:00:00","status":"upcoming","minute":null,"score":null,"match_url":"https://www.flashscore.com/match/EXYFRef3/","tip":{"market":"1 — Pobeda: Serbia U19","tip_odds":null,"confidence":50,"stars":2,"explanation":"Serbia U19: 0pt / 0 utakmica = prosek 1.00. Ukraine U19: 0pt / 0 utakmica = prosek 1.00. Domaćin je jači za 0.00 boda — tip '1 — Pobeda: Serbia U19' sa 50% sigurnosti.","key_factors":[],"stats_breakdown":{"home_form_avg":1.0,"away_form_avg":1.0,"difference":0.0,"home_breakdown":[],"away_breakdown":[]}}},{"id":"fs_jJucpA84","source":"flashscore","league":"Football","league_url":null,"home_team":"Spain","away_team":"Austria","kickoff":"2026-07-02T19:00:00","status":"upcoming","minute":null,"score":null,"match_url":"https://www.flashscore.com/match/jJucpA84/","tip":{"market":"1 — Pobeda: Spain","tip_odds":1.33,"confidence":50,"stars":2,"explanation":"Spain: 0pt / 0 utakmica = prosek 1.00. Austria: 0pt / 0 utakmica = prosek 1.00. Domaćin je jači za 0.00 boda — tip '1 — Pobeda: Spain' sa 50% sigurnosti.","key_factors":[],"stats_breakdown":{"home_form_avg":1.0,"away_form_avg":1.0,"difference":0.0,"home_breakdown":[],"away_breakdown":[]}},"odds":{"home":1.33,"draw":5.25,"away":8.75}},{"id":"fs_6BqAZhfn","source":"flashscore","league":"Football","league_url":null,"home_team":"Portugal","away_team":"Croatia","kickoff":"2026-07-02T23:00:00","status":"upcoming","minute":null,"score":null,"match_url":"https://www.flashscore.com/match/6BqAZhfn/","tip":{"market":"1 — Pobeda: Portugal","tip_odds":1.73,"confidence":50,"stars":2,"explanation":"Portugal: 0pt / 0 utakmica = prosek 1.00. Croatia: 0pt / 0 utakmica = prosek 1.00. Domaćin je jači za 0.00 boda — tip '1 — Pobeda: Portugal' sa 50% sigurnosti.","key_factors":[],"stats_breakdown":{"home_form_avg":1.0,"away_form_avg":1.0,"difference":0.0,"home_breakdown":[],"away_breakdown":[]}},"odds":{"home":1.73,"draw":3.7,"away":4.6}},{"id":"fs_boxn4JpA","source":"flashscore","league":"Football","league_url":null,"home_team":"BATE","away_team":"FC Gomel","kickoff":"2026-07-02T15:00:00","status":"upcoming","minute":null,"score":null,"match_url":"https://www.flashscore.com/match/boxn4JpA/","tip":{"market":"1 — Pobeda: BATE","tip_odds":3.9,"confidence":50,"stars":2,"explanation":"BATE: 0pt / 0 utakmica = prosek 1.00. FC Gomel: 0pt / 0 utakmica = prosek 1.00. Domaćin je jači za 0.00 boda — tip '1 — Pobeda: BATE' sa 50% sigurnosti.","key_factors":[],"stats_breakdown":{"home_form_avg":1.0,"away_form_avg":1.0,"difference":0.0,"home_breakdown":[],"away_breakdown":[]}},"odds":{"home":3.9,"draw":3.1,"away":1.83}},{"id":"fs_lbPXfF7d","source":"flashscore","league":"Football","league_url":null,"home_team":"FC Minsk","away_team":"Din. Minsk","kickoff":"2026-07-02T17:00:00","status":"upcoming","minute":null,"score":null,"match_url":"https://www.flashscore.com/match/lbPXfF7d/","tip":{"market":"1 — Pobeda: FC Minsk","tip_odds":4.8,"confidence":50,"stars":2,"explanation":"FC Minsk: 0pt / 0 utakmica = prosek 1.00. Din. Minsk: 0pt / 0 utakmica = prosek 1.00. Domaćin je jači za 0.00 boda — tip '1 — Pobeda: FC Minsk' sa 50% sigurnosti.","key_factors":[],"stats_breakdown":{"home_form_avg":1.0,"away_form_avg":1.0,"difference":0.0,"home_breakdown":[],"away_breakdown":[]}},"odds":{"home":4.8,"draw":3.7,"away":1.55}},{"id":"fs_QVKCjMJD","source":"flashscore","league":"Football","league_url":null,"home_team":"Cuiaba","away_team":"America MG","kickoff":"2026-07-02T23:00:00","status":"upcoming","minute":null,"score":null,"match_url":"https://www.flashscore.com/match/QVKCjMJD/","tip":{"market":"1 — Pobeda: Cuiaba","tip_odds":1.8,"confidence":50,"stars":2,"explanation":"Cuiaba: 0pt / 0 utakmica = prosek 1.00. America MG: 0pt / 0 utakmica = prosek 1.00. Domaćin je jači za 0.00 boda — tip '1 — Pobeda: Cuiaba' sa 50% sigurnosti.","key_factors":[],"stats_breakdown":{"home_form_avg":1.0,"away_form_avg":1.0,"difference":0.0,"home_breakdown":[],"away_breakdown":[]}},"odds":{"home":1.8,"draw":3.2,"away":4.5}},{"id":"fs_pUpLzpL8","source":"flashscore","league":"Football","league_url":null,"home_team":"Huachipato","away_team":"D. Concepcion","kickoff":"2026-07-02T22:00:00","status":"upcoming","minute":null,"score":null,"match_url":"https://www.flashscore.com/match/pUpLzpL8/","tip":{"market":"1 — Pobeda: Huachipato","tip_odds":2.1,"confidence":50,"stars":2,"explanation":"Huachipato: 0pt / 0 utakmica = prosek 1.00. D. Concepcion: 0pt / 0 utakmica = prosek 1.00. Domaćin je jači za 0.00 boda — tip '1 — Pobeda: Huachipato' sa 50% sigurnosti.","key_factors":[],"stats_breakdown":{"home_form_avg":1.0,"away_form_avg":1.0,"difference":0.0,"home_breakdown":[],"away_breakdown":[]}},"odds":{"home":2.1,"draw":3.1,"away":3.1}},{"id":"fs_rF8YhcB4","source":"flashscore","league":"Football","league_url":null,"home_team":"Kuressaare","away_team":"Flora","kickoff":"2026-07-02T16:00:00","status":"upcoming","minute":null,"score":null,"match_url":"https://www.flashscore.com/match/rF8YhcB4/","tip":{"market":"1 — Pobeda: Kuressaare","tip_odds":7.0,"confidence":50,"stars":2,"explanation":"Kuressaare: 0pt / 0 utakmica = prosek 1.00. Flora: 0pt / 0 utakmica = prosek 1.00. Domaćin je jači za 0.00 boda — tip '1 — Pobeda: Kuressaare' sa 50% sigurnosti.","key_factors":[],"stats_breakdown":{"home_form_avg":1.0,"away_form_avg":1.0,"difference":0.0,"home_breakdown":[],"away_breakdown":[]}},"odds":{"home":7.0,"draw":5.0,"away":1.3}},{"id":"fs_xfz6emae","source":"flashscore","league":"Football","league_url":null,"home_team":"Tallinna Wolves","away_team":"Tabasalu","kickoff":"2026-07-02T17:30:00","status":"upcoming","minute":null,"score":null,"match_url":"https://www.flashscore.com/match/xfz6emae/","tip":{"market":"1 — Pobeda: Tallinna Wolves","tip_odds":13.5,"confidence":50,"stars":2,"explanation":"Tallinna Wolves: 0pt / 0 utakmica = prosek 1.00. Tabasalu: 0pt / 0 utakmica = prosek 1.00. Domaćin je jači za 0.00 boda — tip '1 — Pobeda: Tallinna Wolves' sa 50% sigurnosti.","key_factors":[],"stats_breakdown":{"home_form_avg":1.0,"away_form_avg":1.0,"difference":0.0,"home_breakdown":[],"away_breakdown":[]}},"odds":{"home":13.5,"draw":10.5,"away":1.09}}],"last_updated":"04:32"}